Day063 - mod N Counter/design.sv
module modNCounter(count, clk, reset);
  parameter mod = 10;
  parameter length = 4;
  input clk, reset;
  output reg [length-1:0] count;
  
  always @(posedge clk or posedge reset)
  begin
    if (reset == 1)
      count <= 0;
    else
    begin
      if (count == mod)
        count <= 0;
      else
        count <= count + 1;
    end
  end
endmodule

Day063 - mod N Counter/testbench.sv
module testBench_modNCounter();
  reg clk, reset;
  wire [3:0] count;  // Adjust the wire width to match the counter output

  // Instantiate the modNCounter module
  modNCounter #(10, 4) modNCount(count, clk, reset);  // Match parameters

  // Clock generation
  initial begin
    clk = 0;
    forever #5 clk = ~clk;  // Toggle clock every 5 time units
  end

  // Stimulus
  initial begin
    reset = 1;  // Assert reset
    #10 reset = 0;  // Deassert reset after 10 time units
  end

  // Dumping waveform data
  initial begin
    $dumpfile("dump.vcd");
    $dumpvars(1, testBench_modNCounter);
  end

  // Monitor count values
  initial begin
    $monitor($time, " count = %b", count);
  end

  // End simulation after a specified time
  initial begin
    #500 $finish;
  end

endmodule

Day063 - mod N Counter/dump.vcd
$date
	Sat Oct 19 04:56:21 2024
$end
$version
	Icarus Verilog
$end
$timescale
	1s
$end
$scope module testBench_modNCounter $end
$var wire 4 ! count [3:0] $end
$var reg 1 " clk $end
$var reg 1 # reset $end
$upscope $end
$enddefinitions $end
$comment Show the parameter values. $end
$dumpall
$end
#0
$dumpvars
1#
0"
b0 !
$end
#5
1"
#10
0"
0#
#15
b1 !
1"
#20
0"
#25
b10 !
1"
#30
0"
#35
b11 !
1"
#40
0"
#45
b100 !
1"
#50
0"
#55
b101 !
1"
#60
0"
#65
b110 !
1"
#70
0"
#75
b111 !
1"
#80
0"
#85
b1000 !
1"
#90
0"
#95
b1001 !
1"
#100
0"
#105
b1010 !
1"
#110
0"
#115
b0 !
1"
#120
0"
#125
b1 !
1"
#130
0"
#135
b10 !
1"
#140
0"
#145
b11 !
1"
#150
0"
#155
b100 !
1"
#160
0"
#165
b101 !
1"
#170
0"
#175
b110 !
1"
#180
0"
#185
b111 !
1"
#190
0"
#195
b1000 !
1"
#200
0"
#205
b1001 !
1"
#210
0"
#215
b1010 !
1"
#220
0"
#225
b0 !
1"
#230
0"
#235
b1 !
1"
#240
0"
#245
b10 !
1"
#250
0"
#255
b11 !
1"
#260
0"
#265
b100 !
1"
#270
0"
#275
b101 !
1"
#280
0"
#285
b110 !
1"
#290
0"
#295
b111 !
1"
#300
0"
#305
b1000 !
1"
#310
0"
#315
b1001 !
1"
#320
0"
#325
b1010 !
1"
#330
0"
#335
b0 !
1"
#340
0"
#345
b1 !
1"
#350
0"
#355
b10 !
1"
#360
0"
#365
b11 !
1"
#370
0"
#375
b100 !
1"
#380
0"
#385
b101 !
1"
#390
0"
#395
b110 !
1"
#400
0"
#405
b111 !
1"
#410
0"
#415
b1000 !
1"
#420
0"
#425
b1001 !
1"
#430
0"
#435
b1010 !
1"
#440
0"
#445
b0 !
1"
#450
0"
#455
b1 !
1"
#460
0"
#465
b10 !
1"
#470
0"
#475
b11 !
1"
#480
0"
#485
b100 !
1"
#490
0"
#495
b101 !
1"
