Day048 - JK Flip Flop/design.sv
module JK_FlipFlop(Q, Qbar, clk, reset, J, K);
  
  input clk, reset, J, K;
  output reg Q, Qbar;
  
  always @(posedge clk) begin
    if (reset)
      Q <= 1'b0;
    else begin
      case ({J, K})
        2'b00: Q <= Q;      // Hold state
        2'b01: Q <= 1'b0;   // Reset
        2'b10: Q <= 1'b1;   // Set
        2'b11: Q <= ~Q;     // Toggle
      endcase
    end
    Qbar <= ~Q;  // Update Qbar after Q is updated
  end
  
endmodule

Day048 - JK Flip Flop/testbench.sv
module testBench_JKFlipFlop();
  reg clk, reset, J, K;
  wire Q, Qbar;
  
  // Instantiate the JK flip-flop
  JK_FlipFlop JH_flipFlop(Q, Qbar, clk, reset, J, K);
  
  // Generate clock signal
  initial begin
    clk = 1'b0;  
    forever #5 clk = ~clk;  // Clock period is 10 time units
  end
  
  // Test sequence
  initial begin
    reset = 1'b1;  // Start with reset active
    J = 1'b0;
    K = 1'b0;
    
    $dumpfile("dump.vcd");   // For waveform generation
    $dumpvars(1, testBench_JKFlipFlop);
    
    // Monitor the signals
    $monitor($time, " J = %b, K = %b, Q = %b, Qbar = %b", J, K, Q, Qbar);
    
    #10 reset = 1'b0;  // Release reset after 10 time units

    // Test different JK inputs
    #10 J = 1'b0; K = 1'b0;  // Hold state
    #10 J = 1'b0; K = 1'b1;  // Reset state
    #10 J = 1'b1; K = 1'b0;  // Set state
    #10 J = 1'b1; K = 1'b1;  // Toggle state
    
    #20 $finish;  // Give some time after the last test case and finish the simulation
  end
  
endmodule

Day048 - JK Flip Flop/dump.vcd
$date
	Fri Oct 18 05:18:09 2024
$end
$version
	Icarus Verilog
$end
$timescale
	1s
$end
$scope module testBench_JKFlipFlop $end
$var wire 1 ! Qbar $end
$var wire 1 " Q $end
$var reg 1 # J $end
$var reg 1 $ K $end
$var reg 1 % clk $end
$var reg 1 & reset $end
$upscope $end
$enddefinitions $end
$comment Show the parameter values. $end
$dumpall
$end
#0
$dumpvars
1&
0%
0$
0#
x"
x!
$end
#5
0"
1%
#10
0%
0&
#15
1!
1%
#20
0%
#25
1%
#30
0%
1$
#35
1%
#40
0%
0$
1#
#45
1"
1%
#50
0%
1$
#55
0!
0"
1%
#60
0%
#65
1!
1"
1%
