Day050 - T Flip Flop/design.sv
module T_flipFlop(Q, Qbar, clk, reset, T);

  input clk, reset, T;
  output reg Q, Qbar;
  
  always @(posedge clk) begin
    if (reset)
      Q <= 1'b0; 
    else
      Q <= ~T;
      
    Qbar <= ~Q;  
  end

endmodule

Day050 - T Flip Flop/testbench.sv
module testBench_T_flipFlop();
  reg clk, reset, T;
  wire Q, Qbar;
  
  // Instantiate the T flip-flop
  T_flipFlop T_flipFlop(Q, Qbar, clk, reset, T);
  
  // Generate clock signal
  initial begin
    clk = 1'b0;  
    forever #5 clk = ~clk;  // Clock period is 10 time units
  end
  
  // Test sequence
  initial begin
    reset = 1'b1;  // Start with reset active
    T = 1'b0;
    
    $dumpfile("dump.vcd");   // For waveform generation
    $dumpvars(1, testBench_T_flipFlop);
    
    // Monitor the signals
    $monitor($time, " T = %b, Q = %b, Qbar = %b, reset = %b", T, Q, Qbar, reset);
    
    #10 reset = 1'b0;  // Release reset after 10 time units

    // Test different T input values
    #10 T = 1'b0;  
    #10 T = 1'b1;  
    #10 T = 1'b0;  
    #10 T = 1'b1;  

    #20 $finish;  // End the simulation
  end
  
endmodule

Day050 - T Flip Flop/dump.vcd
$date
	Fri Oct 18 05:51:28 2024
$end
$version
	Icarus Verilog
$end
$timescale
	1s
$end
$scope module testBench_T_flipFlop $end
$var wire 1 ! Qbar $end
$var wire 1 " Q $end
$var reg 1 # T $end
$var reg 1 $ clk $end
$var reg 1 % reset $end
$upscope $end
$enddefinitions $end
$comment Show the parameter values. $end
$dumpall
$end
#0
$dumpvars
1%
0$
0#
x"
x!
$end
#5
0"
1$
#10
0$
0%
#15
1!
1"
1$
#20
0$
#25
0!
1$
#30
0$
1#
#35
0"
1$
#40
0$
0#
#45
1!
1"
1$
#50
0$
1#
#55
0!
0"
1$
#60
0$
#65
1!
1$
