Day049 - D flip flop/design.sv
module D_flipFlop(Q, Qbar, clk, reset, D);

  input clk, reset, D;
  output reg Q, Qbar;
  
  always @(posedge clk) begin
    if (reset)
      Q <= 1'b0; 
    else
      Q <= D;     
      
    Qbar <= ~Q;  
  end

endmodule

Day049 - D flip flop/testbench.sv
module testBench_D_flipFlop();
  reg clk, reset, D;
  wire Q, Qbar;
  
  // Instantiate the D flip-flop
  D_flipFlop D_flipFlop(Q, Qbar, clk, reset, D);
  
  // Generate clock signal
  initial begin
    clk = 1'b0;  
    forever #5 clk = ~clk;  // Clock period is 10 time units
  end
  
  // Test sequence
  initial begin
    reset = 1'b1;  // Start with reset active
    D = 1'b0;
    
    $dumpfile("dump.vcd");   // For waveform generation
    $dumpvars(1, testBench_D_flipFlop);
    
    // Monitor the signals
    $monitor($time, " D = %b, Q = %b, Qbar = %b, reset = %b", D, Q, Qbar, reset);
    
    #10 reset = 1'b0;  // Release reset after 10 time units

    // Test different D input values
    #10 D = 1'b0;  // Q should stay 0
    #10 D = 1'b1;  // Q should become 1
    #10 D = 1'b0;  // Q should become 0
    #10 D = 1'b1;  // Q should become 1

    #20 $finish;  // End the simulation
  end
  
endmodule

Day049 - D flip flop/dump.vcd
$date
	Fri Oct 18 05:36:40 2024
$end
$version
	Icarus Verilog
$end
$timescale
	1s
$end
$scope module testBench_D_flipFlop $end
$var wire 1 ! Qbar $end
$var wire 1 " Q $end
$var reg 1 # D $end
$var reg 1 $ clk $end
$var reg 1 % reset $end
$upscope $end
$enddefinitions $end
$comment Show the parameter values. $end
$dumpall
$end
#0
$dumpvars
1%
0$
0#
x"
x!
$end
#5
0"
1$
#10
0$
0%
#15
1!
1$
#20
0$
#25
1$
#30
0$
1#
#35
1"
1$
#40
0$
0#
#45
0!
0"
1$
#50
0$
1#
#55
1!
1"
1$
#60
0$
#65
0!
1$
