Day039 - binary to 2_complement/design.sv
// Code your design here
module binary_to_2Com_4Bit(complement_2,B);
  input [3:0] B;
  output [3:0] complement_2;
  
  assign complement_2 = (~B)+1;
  
  
endmodule

Day039 - binary to 2_complement/testbench.sv
// Code your testbench here
// or browse Examples
module testBench_2Com();
  reg [3:0] B;
  wire [3:0] complement_2;
  integer i;
  
  binary_to_2Com_4Bit com2(complement_2,B);
  
  initial begin
    B = 4'b0000;
    
    $dumpfile("dump.vcd");
    $dumpvars(1,testBench_2Com);
    
    $monitor($time," B = %b, 2's = %b",B,complement_2);
    for(i=0;i<=16;i=i+1)
      begin
        #5 B = i;
      end
    $finish;
    
  end
  
endmodule

Day039 - binary to 2_complement/dump.vcd
$date
	Thu Oct 17 00:21:41 2024
$end
$version
	Icarus Verilog
$end
$timescale
	1s
$end
$scope module testBench_2Com $end
$var wire 4 ! complement_2 [3:0] $end
$var reg 4 " B [3:0] $end
$var integer 32 # i [31:0] $end
$upscope $end
$enddefinitions $end
$comment Show the parameter values. $end
$dumpall
$end
#0
$dumpvars
b0 #
b0 "
b0 !
$end
#5
b1 #
#10
b1111 !
b10 #
b1 "
#15
b1110 !
b11 #
b10 "
#20
b1101 !
b100 #
b11 "
#25
b1100 !
b101 #
b100 "
#30
b1011 !
b110 #
b101 "
#35
b1010 !
b111 #
b110 "
#40
b1001 !
b1000 #
b111 "
#45
b1000 !
b1001 #
b1000 "
#50
b111 !
b1010 #
b1001 "
#55
b110 !
b1011 #
b1010 "
#60
b101 !
b1100 #
b1011 "
#65
b100 !
b1101 #
b1100 "
#70
b11 !
b1110 #
b1101 "
#75
b10 !
b1111 #
b1110 "
#80
b1 !
b10000 #
b1111 "
#85
b0 !
b10001 #
b0 "
