Day008 - Half and Full Subtractor/002-fullSubtractor_1Bit/design.sv
// Code your design here
module fullSubtractor_1Bit(diff,borrow,A,B,Bin);
  // input decleration
  input A,B,Bin;
  
  // output decleration
  output diff,borrow;
  
  assign diff = A^B^Bin;
  assign borrow = (~A)&(B|Bin)|(B&Bin);
  
endmodule

Day008 - Half and Full Subtractor/002-fullSubtractor_1Bit/testbench.sv
// Code your testbench here
// or browse Examples
module testBench_fullSubtractor_1Bit();
   // decleration of input
  reg A,B,Bin;
  integer i = 0;
  
  // decleration of output
  wire diff;
  wire borrow;
  
  // instantiation
  fullSubtractor_1Bit fullSubtractor(diff,borrow,A,B,Bin);
  
  // stimulation block
  initial begin
    // initialisation
    A=0;B=0;Bin=0;
    
    // creating dumpfile
    $dumpfile("dump.vcd");
    $dumpvars(1,testBench_fullSubtractor_1Bit);
    
    // monitoring changing values
    $monitor($time,"A=%b,B=%b,Bin=%b,D=%b,B=%b",A,B,Bin,diff,borrow);
    
    // differnt input values
    for(int i=0;i<8;i=i+1)
      begin
        {A,B}=i;#10;
      end
    $finish;
    
  end
  
endmodule

Day008 - Half and Full Subtractor/002-fullSubtractor_1Bit/dump.vcd
$date
	Sun Sep 15 10:49:34 2024
$end
$version
	Icarus Verilog
$end
$timescale
	1s
$end
$scope module testBench_fullSubtractor_1Bit $end
$var wire 1 ! diff $end
$var wire 1 " borrow $end
$var reg 1 # A $end
$var reg 1 $ B $end
$var reg 1 % Bin $end
$var integer 32 & i [31:0] $end
$upscope $end
$enddefinitions $end
$comment Show the parameter values. $end
$dumpall
$end
#0
$dumpvars
b0 &
0%
0$
0#
0"
0!
$end
#10
1"
1!
1$
#20
0"
1#
0$
#30
0!
1$
#40
0#
0$
#50
1"
1!
1$
#60
0"
1#
0$
#70
0!
1$
