Day038 - binary to grey convertor/design.sv
// Code your design here
module binary_to_grey_4Bit(G,B);
  input [3:0] B;
  output [3:0] G;
  
  assign G[3] = B[3];
  assign G[2] = B[3]^B[2];
  assign G[1] = B[2]^B[1];
  assign G[0] = B[1]^B[0];
  
endmodule

Day038 - binary to grey convertor/testbench.sv
// Code your testbench here
// or browse Examples
module testBench_BtoG();
  reg [3:0] B;
  output [3:0] G;
  integer i ;
  
  binary_to_grey_4Bit BtoG(G,B);
  
  initial begin
    B = 4'b0000;
    
    $dumpfile("dump.vcd");
    $dumpvars(1,testBench_BtoG);
    
    $monitor($time," B = %b ,G=%b",B,G);
    for(i=0;i<=16;i++)
      begin
        #5 B = i;
      end
    $finish;
    
  end
  
endmodule

Day038 - binary to grey convertor/dump.vcd
$date
	Thu Oct 17 00:08:40 2024
$end
$version
	Icarus Verilog
$end
$timescale
	1s
$end
$scope module testBench_BtoG $end
$var wire 4 ! G [3:0] $end
$var reg 4 " B [3:0] $end
$var integer 32 # i [31:0] $end
$upscope $end
$enddefinitions $end
$comment Show the parameter values. $end
$dumpall
$end
#0
$dumpvars
b0 #
b0 "
b0 !
$end
#5
b1 #
#10
b1 !
b10 #
b1 "
#15
b11 !
b11 #
b10 "
#20
b10 !
b100 #
b11 "
#25
b110 !
b101 #
b100 "
#30
b111 !
b110 #
b101 "
#35
b101 !
b111 #
b110 "
#40
b100 !
b1000 #
b111 "
#45
b1100 !
b1001 #
b1000 "
#50
b1101 !
b1010 #
b1001 "
#55
b1111 !
b1011 #
b1010 "
#60
b1110 !
b1100 #
b1011 "
#65
b1010 !
b1101 #
b1100 "
#70
b1011 !
b1110 #
b1101 "
#75
b1001 !
b1111 #
b1110 "
#80
b1000 !
b10000 #
b1111 "
#85
b0 !
b10001 #
b0 "
