Day007 - Half and Full Adder/002-fullAdder_1Bit/design.sv
// Code your design here
// gate-level-modelling of fullAdder_1Bit
module fullAdder_1Bit(output sum,carry,
  input A,B,Cin);
  
  // internal nets
  wire w1,w2,w3;
  
  // sum logic
  xor xor1(w1,A,B);
  xor xor2(sum,w1,Cin);
  
//   carry logic
  and and1(w2,A,B);
  and and2(w3,w1,Cin);
  
  // final output
  or or1(carry,w2,w3);
  
endmodule

Day007 - Half and Full Adder/002-fullAdder_1Bit/testbench.sv
// Code your testbench here
// or browse Examples
module testBench_fullAdder_1Bit();
  // declaring input
  reg A,B,Cin;
  
  // declaring output
  wire sum,carry;
  
  // instantiation
  fullAdder_1Bit fullAdder(.sum(sum),.carry(carry),.A(A),.B(B),.Cin(Cin));
  
  // stimulation code
  initial begin
    // initialising reg
    A=0;B=0;Cin=0;
    
    // creating dumpfile
    $dumpfile("dump.vcd");
    $dumpvars(1,testBench_fullAdder_1Bit);
    
    // monitoring variabloe changes
    $monitor($time,"A=%b,B=%b,Cin=%b,sum=%b,carry=%b",A,B,Cin,sum,carry);
    A=0;B=0;Cin=0;#10;
    A=0;B=0;Cin=1;#10;
    A=0;B=1;Cin=0;#10;
    A=0;B=1;Cin=1;#10;
    A=1;B=0;Cin=0;#10;
    A=1;B=0;Cin=1;#10;
    A=1;B=1;Cin=0;#10;
    A=1;B=1;Cin=1;#10;
    
    $finish;
    
  end
  
endmodule

Day007 - Half and Full Adder/002-fullAdder_1Bit/dump.vcd
$date
	Sun Sep 15 03:17:27 2024
$end
$version
	Icarus Verilog
$end
$timescale
	1s
$end
$scope module testBench_fullAdder_1Bit $end
$var wire 1 ! sum $end
$var wire 1 " carry $end
$var reg 1 # A $end
$var reg 1 $ B $end
$var reg 1 % Cin $end
$upscope $end
$enddefinitions $end
$comment Show the parameter values. $end
$dumpall
$end
#0
$dumpvars
0%
0$
0#
0"
0!
$end
#10
1!
1%
#20
0%
1$
#30
1"
0!
1%
#40
0"
1!
0%
0$
1#
#50
1"
0!
1%
#60
0%
1$
#70
1!
1%
